fibocli.py
fiboseqcli-0.1.2.dist-info/DESCRIPTION.rst
fiboseqcli-0.1.2.dist-info/entry_points.txt
fiboseqcli-0.1.2.dist-info/METADATA
fiboseqcli-0.1.2.dist-info/metadata.json
fiboseqcli-0.1.2.dist-info/RECORD
fiboseqcli-0.1.2.dist-info/top_level.txt
fiboseqcli-0.1.2.dist-info/WHEEL
scripts/__init__.py
scripts/hello_world.py
