Metadata-Version: 2.0
Name: fiboseqcli
Version: 0.1.2
Summary: Sample Fibonacci sequence tool.
Home-page: http://balameb.primate.tech/python/2017/03/15/distributing-python-packages.html
Author: Jose Torres
Author-email: torres@balameb.com
License: MIT
Keywords: fibonacci example examples
Platform: UNKNOWN
Requires-Dist: Click
